{"Zipcode":{"0":94102,"1":94102,"2":94102,"3":94103,"4":94107,"5":94108,"6":94109,"7":94109,"8":94110,"9":94110,"10":94112,"11":94112,"12":94114,"13":94114,"14":94115,"15":94115,"16":94116,"17":94116,"18":94117,"19":94118,"20":94121,"21":94122,"22":94123,"23":94124,"24":94127,"25":94127,"26":94127,"27":94131,"28":94132,"29":94133,"30":94133,"31":94134,"32":94134},"Neighborhood":{"0":"Hayes Valley","1":"Tenderloin","2":"North of Market","3":"South of Market","4":"Potrero Hill","5":"Chinatown\u00a0","6":"Polk","7":"Russian Hill (Nob Hill)","8":"Inner Mission","9":"Bernal Heights","10":"Ingelside-Excelsior","11":"Crocker-Amazon","12":"Castro","13":"Noe Valley\u00a0","14":"Western Addition","15":"Japantown","16":"Parkside","17":"Forest Hill\u00a0","18":"Haight-Ashbury","19":"Inner Richmond\u00a0","20":"Outer Richmond\u00a0","21":"Sunset","22":"Marina","23":"Bayview-Hunters Point\u00a0","24":"St. Francis Wood","25":"Miraloma","26":"West Portal","27":"Twin Peaks-Glen Park","28":"Lake Merced\u00a0","29":"North Beach","30":"Chinatown","31":"Visitacion Valley","32":"Sunnydale"}}